raiblocks/__init__.py
raiblocks/accounts.py
raiblocks/blocks.py
raiblocks/conversion.py
raiblocks/rpc.py
raiblocks/version.py
raiblocks-1.1.0.dist-info/DESCRIPTION.rst
raiblocks-1.1.0.dist-info/METADATA
raiblocks-1.1.0.dist-info/RECORD
raiblocks-1.1.0.dist-info/WHEEL
raiblocks-1.1.0.dist-info/metadata.json
raiblocks-1.1.0.dist-info/top_level.txt
