Metadata-Version: 2.0
Name: raiblocks
Version: 1.1.0
Summary: RaiBlocks Python RPC client for rai_node
Home-page: https://github.com/dourvaris/raiblocks-python
Author: Daniel Dourvaris
Author-email: dourvaris@gmail.com
License: MIT
Platform: UNKNOWN
Classifier: License :: OSI Approved :: MIT License
Classifier: Programming Language :: Python
Classifier: Programming Language :: Python :: 2.6
Classifier: Programming Language :: Python :: 2.7
Classifier: Programming Language :: Python :: 3
Classifier: Programming Language :: Python :: 3.3
Classifier: Programming Language :: Python :: 3.4
Classifier: Programming Language :: Python :: 3.5
Classifier: Programming Language :: Python :: 3.6
Classifier: Programming Language :: Python :: Implementation :: CPython
Classifier: Programming Language :: Python :: Implementation :: PyPy
Classifier: Topic :: Software Development :: Libraries
Classifier: Development Status :: 3 - Alpha
Requires-Dist: certifi (==2017.11.5)
Requires-Dist: chardet (==3.0.4)
Requires-Dist: idna (==2.6)
Requires-Dist: ordereddict (==1.1)
Requires-Dist: requests (==2.18.4)
Requires-Dist: six (==1.11.0)
Requires-Dist: urllib3 (==1.22)
